pylist/__init__.py
pylist/cli.py
pylist/downloader.py
pylist/gui.py
pylist/logging_config.py
pylist/utils.py
pylist/assets/how_1.png
pylist/assets/how_2.png
pylist/assets/icon_128.ico
pylist/assets/icon_16.ico
pylist/assets/icon_256.ico
pylist/assets/icon_32.ico
pylist/assets/icon_64.ico
pylist/assets/icon_big.png
pylist/assets/page_1.png
pylist/assets/page_2.png
pylist/assets/page_3.png
pylist/assets/page_4.png
pylist/assets/page_5.png
pylist/assets/splash_small.png
pylist_grab-0.0.5.dist-info/METADATA
pylist_grab-0.0.5.dist-info/WHEEL
pylist_grab-0.0.5.dist-info/entry_points.txt
pylist_grab-0.0.5.dist-info/top_level.txt
pylist_grab-0.0.5.dist-info/RECORD
