Metadata-Version: 2.1
Name: pylist-grab
Version: 0.0.5
Summary: YouTube playlist grabber with metadata injector
Home-page: https://github.com/lewis-morris/pylist-grab
Author: lewis
Author-email: lewis.morris@gmail.com
License: MIT
Requires-Dist: requests ~=2.31.0
Requires-Dist: pytube ~=15.0.0
Requires-Dist: moviepy ~=1.0.3
Requires-Dist: mutagen ~=1.47.0
Requires-Dist: pyside6 ~=6.6.0
Requires-Dist: pyside6-essentials ~=6.6.0
Requires-Dist: setuptools ~=68.0.0
Requires-Dist: qt-material ~=2.4.0
